bugspots.py
bugspots3-0.3.0.data/scripts/bugspots.py
bugspots3-0.3.0.dist-info/DESCRIPTION.rst
bugspots3-0.3.0.dist-info/METADATA
bugspots3-0.3.0.dist-info/RECORD
bugspots3-0.3.0.dist-info/WHEEL
bugspots3-0.3.0.dist-info/metadata.json
bugspots3-0.3.0.dist-info/top_level.txt
