Metadata-Version: 2.0
Name: bugspots3
Version: 0.3.0
Summary: 
